{
  "course": "C165",
  "clusters": [
    {
      "cluster_id": "C165_1",
      "title": "Assessment Failure Anxiety",
      "root_cause_summary": "Students feel defeated and discouraged after repeated failures in assessments despite extensive preparation.",
      "pain_point_ids": [
        "1m70tbw_0",
        "1lju7av_0",
        "1jhe6hs_0"
      ],
      "is_potential": false
    },
    {
      "cluster_id": "C165_2",
      "title": "Overwhelming Course Material",
      "root_cause_summary": "Students feel overwhelmed by the extensive and complex course material, leading to stress.",
      "pain_point_ids": [
        "1k9lt3i_0",
        "1lbptfq_0"
      ],
      "is_potential": false
    },
    {
      "cluster_id": "C165_3",
      "title": "Study Method Challenges",
      "root_cause_summary": "Students struggle to find effective study methods for the course, impacting their learning experience.",
      "pain_point_ids": [
        "1km61i6_0",
        "1lkbuqw_0"
      ],
      "is_potential": false
    },
    {
      "cluster_id": "C165_4",
      "title": "Course Retake Process Complexity",
      "root_cause_summary": "Students find the process for retaking the course to be lengthy and complicated, creating barriers to further learning.",
      "pain_point_ids": [
        "1m4ahj1_0"
      ],
      "is_potential": true
    },
    {
      "cluster_id": "C165_5",
      "title": "Financial Aid Anxiety",
      "root_cause_summary": "Students feel anxious about the loss of financial aid due to unclear academic requirements.",
      "pain_point_ids": [
        "1m6qkif_0"
      ],
      "is_potential": true
    }
  ],
  "alert_threshold": 2,
  "alerts": [
    {
      "cluster_id": "C165_1",
      "summary": "Students feel defeated and discouraged after repeated failures in assessments despite extensive preparation.",
      "post_count": 3,
      "detected_on": "2025-07-25T07:46:38.856855Z"
    },
    {
      "cluster_id": "C165_2",
      "summary": "Students feel overwhelmed by the extensive and complex course material, leading to stress.",
      "post_count": 2,
      "detected_on": "2025-07-25T07:46:38.856880Z"
    },
    {
      "cluster_id": "C165_3",
      "summary": "Students struggle to find effective study methods for the course, impacting their learning experience.",
      "post_count": 2,
      "detected_on": "2025-07-25T07:46:38.856884Z"
    }
  ]
}