{
  "course": "D075",
  "clusters": [
    {
      "cluster_id": "D075_1",
      "title": "Terminology Confusion",
      "root_cause_summary": "Students are struggling to understand course terminology and definitions.",
      "pain_point_ids": [
        "1k5jaj4_0"
      ],
      "is_potential": true
    },
    {
      "cluster_id": "D075_2",
      "title": "Communication Gaps",
      "root_cause_summary": "Lack of communication from mentors regarding course requirements creates uncertainty for students.",
      "pain_point_ids": [
        "1i63ghc_0"
      ],
      "is_potential": true
    },
    {
      "cluster_id": "D075_3",
      "title": "Exam Anxiety",
      "root_cause_summary": "Students feel stressed after failing exams, particularly due to unforeseen changes in answers.",
      "pain_point_ids": [
        "1hqh4ig_0"
      ],
      "is_potential": true
    },
    {
      "cluster_id": "D075_4",
      "title": "Resource Overload",
      "root_cause_summary": "Students feel overwhelmed and confused despite using available resources.",
      "pain_point_ids": [
        "1kfurfj_0"
      ],
      "is_potential": true
    },
    {
      "cluster_id": "D075_5",
      "title": "Material Complexity",
      "root_cause_summary": "Students are overwhelmed and confused by the complexity of course material, leading to fears of failure.",
      "pain_point_ids": [
        "1kw44vc_0"
      ],
      "is_potential": true
    }
  ],
  "alert_threshold": 2,
  "alerts": []
}